with_tempfile/__init__.py
with_tempfile/defs.py
with_tempfile/impl.py
with_tempfile/pathutil.py
with_tempfile/py.typed
with_tempfile/temputil.py
with_tempfile-0.1.1.dist-info/METADATA
with_tempfile-0.1.1.dist-info/WHEEL
with_tempfile-0.1.1.dist-info/RECORD
