Metadata-Version: 2.4
Name: with-tempfile
Version: 0.1.1
Summary: Create a temporary file, take care of removing it if needed
Project-URL: Homepage, https://devel.ringlet.net/sysutils/with-tempfile/
Project-URL: Changes, https://devel.ringlet.net/sysutils/with-tempfile/changes/
Project-URL: Issue Tracker, https://gitlab.com/ppentchev/with-tempfile/-/issues
Project-URL: Source Code, https://gitlab.com/ppentchev/with-tempfile
Author-email: Peter Pentchev <roam@ringlet.net>
License-Expression: BSD-2-Clause
Classifier: Development Status :: 4 - Beta
Classifier: Intended Audience :: Developers
Classifier: Operating System :: OS Independent
Classifier: Programming Language :: Python
Classifier: Programming Language :: Python :: 3
Classifier: Programming Language :: Python :: 3 :: Only
Classifier: Programming Language :: Python :: 3.11
Classifier: Programming Language :: Python :: 3.12
Classifier: Programming Language :: Python :: 3.13
Classifier: Programming Language :: Python :: 3.14
Classifier: Topic :: Software Development :: Libraries
Classifier: Topic :: Software Development :: Libraries :: Python Modules
Classifier: Topic :: System :: Filesystems
Classifier: Typing :: Typed
Requires-Python: >=3.11
